Metadata-Version: 2.1
Name: gpterminal
Version: 0.1.8
Summary: A CLI tool to interact with GPT-3/GPT-4, answer Git questions, and execute commands
Home-page: https://github.com/yourusername/gpterminal
Author: Your Name
Author-email: your.email@example.com
Classifier: Development Status :: 3 - Alpha
Classifier: Intended Audience :: Developers
Classifier: License :: OSI Approved :: MIT License
Classifier: Operating System :: OS Independent
Classifier: Programming Language :: Python :: 3
Classifier: Programming Language :: Python :: 3.6
Classifier: Programming Language :: Python :: 3.7
Classifier: Programming Language :: Python :: 3.8
Classifier: Programming Language :: Python :: 3.9
Requires-Python: >=3.6
